verilog/d_flip_flop.v
module d_flip_flop (
    input wire d,      
    input wire clk,    
    output reg q      
);

    always @(posedge clk) begin
        q <= d;        
    end

endmodule

verilog/four_bit_register.v
module four_bit_register(input wire clk, input wire [3:0] d, output wire [3:0] q);
    d_flip_flop FF0 (.clk(clk), .d(d[0]), .q(q[0]));
    d_flip_flop FF1 (.clk(clk), .d(d[1]), .q(q[1]));
    d_flip_flop FF2 (.clk(clk), .d(d[2]), .q(q[2]));
    d_flip_flop FF3 (.clk(clk), .d(d[3]), .q(q[3]));
endmodule

verilog/four_bit_adder_cla.v
module four_bit_adder_cla(
    input wire [3:0] a, 
    input wire [3:0] b, 
    input wire carry,
    output wire [3:0] sum, 
    output wire out_carry
);
    wire p0, p1, p2, p3;
    wire g0, g1, g2, g3;

    xor (p0, a[0], b[0]);
    xor (p1, a[1], b[1]);
    xor (p2, a[2], b[2]);
    xor (p3, a[3], b[3]);

    and (g0, a[0], b[0]);
    and (g1, a[1], b[1]);
    and (g2, a[2], b[2]);
    and (g3, a[3], b[3]);



    wire intermediate_c0;
    and (intermediate_c0, p0, carry_reg);
    or  (c0, intermediate_c0, g0);

    // Stage 2
    wire intermediate_c11, intermediate_c12, inter_c13;
    and (intermediate_c11, intermediate_c0, p1);
    and (intermediate_c12, g0, p1);
    or  (inter_c13, g1, intermediate_c11);
    or  (c1, inter_c13, intermediate_c12);

    // Stage 3
    wire intermediate_c21, intermediate_c22, intermediate_c23, intermediate_c24, inter_c26;
    and (intermediate_c21, p2, intermediate_c11);
    and (intermediate_c22, intermediate_c12, p2);
    and (intermediate_c23, g1, p2);
    or  (intermediate_c24, g2, intermediate_c21);
    or  (inter_c26, intermediate_c24, intermediate_c22);
    or  (c2, inter_c26, intermediate_c23);

    // Stage 4
    wire intermediate_c31, intermediate_c32, intermediate_c33, intermediate_c34;
    wire intermediate_c35, inter_c36, inter_c37;
    and (intermediate_c31, p3, intermediate_c21);
    and (intermediate_c32, intermediate_c22, p3);
    and (intermediate_c33, intermediate_c23, p3);
    and (intermediate_c34, g2, p3);
    or   (intermediate_c35, g3, intermediate_c31);
    or  (inter_c36, intermediate_c35, intermediate_c32);
    or  (inter_c37, inter_c36, intermediate_c33);
    or  (out_carry, inter_c37, intermediate_c34);

    xor (sum[0], p0, carry);
    xor (sum[1], p1, c0);
    xor (sum[2], p2, c1);
    xor (sum[3], p3, c2);

endmodule

verilog/tb_four_bit_adder_cla.v
module tb_four_bit_adder_cla;
    reg clk;
    reg [3:0] a, b;
    reg carry;
    wire [3:0] sum;
    wire out_carry;
    wire [3:0] a_reg, b_reg, sum_reg;
    wire carry_reg, out_carry_reg;
    four_bit_register A_reg (.clk(clk), .d(a), .q(a_reg));
    four_bit_register B_reg (.clk(clk), .d(b), .q(b_reg));
    d_flip_flop C_reg (.clk(clk), .d(carry), .q(carry_reg));
    four_bit_adder_cla UUT (
        .a(a_reg), 
        .b(b_reg),
        .carry(carry_reg),
        .sum(sum), 
        .out_carry(out_carry)
    );
    four_bit_register SUM_reg (.clk(clk), .d(sum), .q(sum_reg));
    d_flip_flop COUT_reg (.clk(clk), .d(out_carry), .q(out_carry_reg));
    initial begin
    $dumpfile("waveform.vcd");  
    $dumpvars(0, tb_four_bit_adder_cla); 
    end

    initial begin
      clk = 0;
      a = 4'b0000;
      b = 4'b0000;
      carry = 0;
        $monitor("time=%0t | clock=%b | a=%b | b=%b | carry=%b |out_carry=%b | sum=%b ", 
        $time, clk, a_reg, b_reg, carry, out_carry_reg, sum_reg);
    
        #15 a = 4'b0001; b = 4'b0001; carry = 0;    
        #10                  

        #5 a = 4'b0011; b = 4'b0011; carry = 1;    
        #10 

        #5 a = 4'b0111; b = 4'b0101; carry = 0;
        #10

        #5 a = 4'b1111; b = 4'b0001; carry = 1;
        #10 

        #5 a = 4'b0101; b = 4'b0011; carry = 1;
        #10 
         $finish;
    end
    always #5 clk = ~clk; 
endmodule

verilog/waveform.vcd
$date
	Wed Nov 20 17:32:43 2024
$end
$version
	Icarus Verilog
$end
$timescale
	1s
$end
$scope module tb_four_bit_adder_cla $end
$var wire 4 ! sum_reg [3:0] $end
$var wire 4 " sum [3:0] $end
$var wire 1 # out_carry_reg $end
$var wire 1 $ out_carry $end
$var wire 1 % carry_reg $end
$var wire 4 & b_reg [3:0] $end
$var wire 4 ' a_reg [3:0] $end
$var reg 4 ( a [3:0] $end
$var reg 4 ) b [3:0] $end
$var reg 1 * carry $end
$var reg 1 + clk $end
$scope module A_reg $end
$var wire 1 + clk $end
$var wire 4 , d [3:0] $end
$var wire 4 - q [3:0] $end
$scope module FF0 $end
$var wire 1 + clk $end
$var wire 1 . d $end
$var reg 1 / q $end
$upscope $end
$scope module FF1 $end
$var wire 1 + clk $end
$var wire 1 0 d $end
$var reg 1 1 q $end
$upscope $end
$scope module FF2 $end
$var wire 1 + clk $end
$var wire 1 2 d $end
$var reg 1 3 q $end
$upscope $end
$scope module FF3 $end
$var wire 1 + clk $end
$var wire 1 4 d $end
$var reg 1 5 q $end
$upscope $end
$upscope $end
$scope module B_reg $end
$var wire 1 + clk $end
$var wire 4 6 d [3:0] $end
$var wire 4 7 q [3:0] $end
$scope module FF0 $end
$var wire 1 + clk $end
$var wire 1 8 d $end
$var reg 1 9 q $end
$upscope $end
$scope module FF1 $end
$var wire 1 + clk $end
$var wire 1 : d $end
$var reg 1 ; q $end
$upscope $end
$scope module FF2 $end
$var wire 1 + clk $end
$var wire 1 < d $end
$var reg 1 = q $end
$upscope $end
$scope module FF3 $end
$var wire 1 + clk $end
$var wire 1 > d $end
$var reg 1 ? q $end
$upscope $end
$upscope $end
$scope module COUT_reg $end
$var wire 1 + clk $end
$var wire 1 $ d $end
$var reg 1 # q $end
$upscope $end
$scope module C_reg $end
$var wire 1 + clk $end
$var wire 1 * d $end
$var reg 1 % q $end
$upscope $end
$scope module SUM_reg $end
$var wire 1 + clk $end
$var wire 4 @ q [3:0] $end
$var wire 4 A d [3:0] $end
$scope module FF0 $end
$var wire 1 + clk $end
$var wire 1 B d $end
$var reg 1 C q $end
$upscope $end
$scope module FF1 $end
$var wire 1 + clk $end
$var wire 1 D d $end
$var reg 1 E q $end
$upscope $end
$scope module FF2 $end
$var wire 1 + clk $end
$var wire 1 F d $end
$var reg 1 G q $end
$upscope $end
$scope module FF3 $end
$var wire 1 + clk $end
$var wire 1 H d $end
$var reg 1 I q $end
$upscope $end
$upscope $end
$scope module UUT $end
$var wire 4 J a [3:0] $end
$var wire 4 K b [3:0] $end
$var wire 1 L c0 $end
$var wire 1 M c1 $end
$var wire 1 N c2 $end
$var wire 1 % carry $end
$var wire 1 O carry_reg $end
$var wire 1 P g0 $end
$var wire 1 Q g1 $end
$var wire 1 R g2 $end
$var wire 1 S g3 $end
$var wire 1 T inter_c13 $end
$var wire 1 U inter_c26 $end
$var wire 1 V inter_c36 $end
$var wire 1 W inter_c37 $end
$var wire 1 X intermediate_c0 $end
$var wire 1 Y intermediate_c11 $end
$var wire 1 Z intermediate_c12 $end
$var wire 1 [ intermediate_c21 $end
$var wire 1 \ intermediate_c22 $end
$var wire 1 ] intermediate_c23 $end
$var wire 1 ^ intermediate_c24 $end
$var wire 1 _ intermediate_c31 $end
$var wire 1 ` intermediate_c32 $end
$var wire 1 a intermediate_c33 $end
$var wire 1 b intermediate_c34 $end
$var wire 1 c intermediate_c35 $end
$var wire 1 $ out_carry $end
$var wire 1 d p0 $end
$var wire 1 e p1 $end
$var wire 1 f p2 $end
$var wire 1 g p3 $end
$var wire 4 h sum [3:0] $end
$upscope $end
$upscope $end
$enddefinitions $end
$comment Show the parameter values. $end
$dumpall
$end
#0
$dumpvars
bx h
xg
xf
xe
xd
xc
xb
xa
x`
x_
x^
x]
x\
x[
xZ
xY
xX
xW
xV
xU
xT
xS
xR
xQ
xP
zO
xN
xM
xL
bx K
bx J
xI
xH
xG
xF
xE
xD
xC
xB
bx A
bx @
x?
0>
x=
0<
x;
0:
x9
08
bx 7
b0 6
x5
04
x3
02
x1
00
x/
0.
bx -
b0 ,
0+
0*
b0 )
b0 (
bx '
bx &
x%
x$
x#
bx "
bx !
$end
#5
0H
0F
0$
0D
0N
0W
0M
0U
0V
0L
0B
0T
0^
0c
0X
b0 "
b0 A
b0 h
0Y
0Z
0[
0\
0]
0_
0`
0a
0b
0d
0P
0e
0Q
0f
0R
0g
0S
0/
01
03
b0 '
b0 -
b0 J
05
09
0;
0=
b0 &
b0 7
b0 K
0?
0%
1+
#10
0+
#15
1D
b10 "
b10 A
b10 h
1L
1P
0#
0I
0G
0E
b0 !
b0 @
0C
b1 &
b1 7
b1 K
19
b1 '
b1 -
b1 J
1/
18
1.
1+
b1 )
b1 6
b1 (
b1 ,
#20
0+
#25
b10 !
b10 @
1E
1+
#30
1:
10
0+
1*
b11 )
b11 6
b11 (
b11 ,
#35
1F
1M
1T
1B
1Q
b111 "
b111 A
b111 h
1%
b11 &
b11 7
b11 K
1;
b11 '
b11 -
b11 J
11
1+
#40
0+
#45
1H
1N
0D
1U
1Z
0T
1^
1e
0Q
1R
0B
b1100 "
b1100 A
b1100 h
b111 '
b111 -
b111 J
13
0;
b101 &
b101 7
b101 K
1=
0%
1C
b111 !
b111 @
1G
0:
1<
12
1+
0*
b101 )
b101 6
b111 (
b111 ,
#50
0+
#55
1I
0E
b1100 !
b1100 @
0C
1+
#60
0<
14
0+
1*
b1 )
b1 6
b1111 (
b1111 ,
#65
1$
1W
1V
0H
0F
1`
1\
0^
1g
1f
0R
1B
b1 "
b1 A
b1 h
b1111 '
b1111 -
b1111 J
15
b1 &
b1 7
b1 K
0=
1%
1+
#70
0+
#75
0$
0W
0V
1H
0`
b1001 "
b1001 A
b1001 h
0g
1#
0I
0G
b1 !
b1 @
1C
b11 &
b11 7
b11 K
1;
05
b101 '
b101 -
b101 J
01
1:
00
04
1+
b11 )
b11 6
b101 (
b101 ,
#80
0+
#85
b1001 !
b1001 @
1I
0#
1+
